pchecker/__init__.py
pchecker/annotation.py
pchecker/exception.py
pchecker/field.py
pchecker/lifecycle.py
pchecker/param.py
pchecker/store.py
ParameterChecker-0.0.5.dist-info/LICENSE
ParameterChecker-0.0.5.dist-info/METADATA
ParameterChecker-0.0.5.dist-info/WHEEL
ParameterChecker-0.0.5.dist-info/top_level.txt
ParameterChecker-0.0.5.dist-info/RECORD
