Metadata-Version: 2.1
Name: ParameterChecker
Version: 0.0.5
Summary: Parameter manager system
Home-page: https://github.com/lipopo/pchecker
Author: lipo
Author-email: lipo8081@gmail.com
License: UNKNOWN
